distributions_cread/Binomial.py
distributions_cread/Gaussian.py
distributions_cread/General.py
distributions_cread/__init__.py
distributions_cread-0.3.dist-info/METADATA
distributions_cread-0.3.dist-info/WHEEL
distributions_cread-0.3.dist-info/top_level.txt
distributions_cread-0.3.dist-info/RECORD
