Metadata-Version: 2.1
Name: distributions-cread
Version: 0.3
Summary: Gaussian and Binomial distributions
Author: Connor Read
License: UNKNOWN
Platform: UNKNOWN
